odoo/addons/shopinvader_search_engine_assortment/README.rst
odoo/addons/shopinvader_search_engine_assortment/__init__.py
odoo/addons/shopinvader_search_engine_assortment/__manifest__.py
odoo/addons/shopinvader_search_engine_assortment/data/ir_cron.xml
odoo/addons/shopinvader_search_engine_assortment/demo/shopinvader_assortment_demo.xml
odoo/addons/shopinvader_search_engine_assortment/i18n/shopinvader_assortment.pot
odoo/addons/shopinvader_search_engine_assortment/i18n/shopinvader_search_engine_assortment.pot
odoo/addons/shopinvader_search_engine_assortment/models/__init__.py
odoo/addons/shopinvader_search_engine_assortment/models/se_backend.py
odoo/addons/shopinvader_search_engine_assortment/models/se_index.py
odoo/addons/shopinvader_search_engine_assortment/readme/CONTRIBUTORS.rst
odoo/addons/shopinvader_search_engine_assortment/readme/DESCRIPTION.rst
odoo/addons/shopinvader_search_engine_assortment/readme/HISTORY.rst
odoo/addons/shopinvader_search_engine_assortment/static/description/index.html
odoo/addons/shopinvader_search_engine_assortment/tests/__init__.py
odoo/addons/shopinvader_search_engine_assortment/tests/test_product_auto_bind.py
odoo/addons/shopinvader_search_engine_assortment/views/se_backend.xml
odoo_addon_shopinvader_search_engine_assortment-16.0.1.0.1.dist-info/METADATA
odoo_addon_shopinvader_search_engine_assortment-16.0.1.0.1.dist-info/WHEEL
odoo_addon_shopinvader_search_engine_assortment-16.0.1.0.1.dist-info/top_level.txt
odoo_addon_shopinvader_search_engine_assortment-16.0.1.0.1.dist-info/RECORD
