Metadata-Version: 2.1
Name: odoo-addon-shopinvader-search-engine-assortment
Version: 16.0.1.0.1
Summary: Shopinvader Search Engine Assortment
Home-page: https://github.com/shopinvader/odoo-shopinvader
Author: ACSONE SA/NV
License: AGPL-3
Platform: UNKNOWN
Classifier: Programming Language :: Python
Classifier: Framework :: Odoo
Classifier: Framework :: Odoo :: 16.0
Classifier: License :: OSI Approved :: GNU Affero General Public License v3
Requires-Python: >=3.10
Requires-Dist: odoo-addon-product-assortment <16.1dev,>=16.0dev
Requires-Dist: odoo-addon-shopinvader-product <16.1dev,>=16.0dev
Requires-Dist: odoo-addon-shopinvader-search-engine <16.1dev,>=16.0dev
Requires-Dist: odoo <16.1dev,>=16.0a
